[
  {
    "maskuline": "jučerašnji",
    "feminine": "jučerašnja",
    "neutrum": "jučerašnje",
    "ukrainianTranslation": "вчорашній",
    "exampleSentence": "Sjećamo se jučerašnjeg sastanka kao vrlo produktivnog.",
    "ukrainianTranslationSentence": "Ми пам'ятаємо вчорашню зустріч як дуже продуктивну."
  },
  {
    "maskuline": "junački",
    "feminine": "junačka",
    "neutrum": "junačko",
    "ukrainianTranslation": "героїчний",
    "exampleSentence": "Njegov junački čin spašavanja djeteta je pohvaljen.",
    "ukrainianTranslationSentence": "Його героїчний вчинок з порятунку дитини був відзначений."
  },
  {
    "maskuline": "kadetski",
    "feminine": "kadetska",
    "neutrum": "kadetsko",
    "ukrainianTranslation": "кадетський",
    "exampleSentence": "Kadetski turnir u šahu održan je prošlog vikenda.",
    "ukrainianTranslationSentence": "Кадетський шаховий турнір відбувся минулого тижня."
  },
  {
    "maskuline": "kalendarski",
    "feminine": "kalendarska",
    "neutrum": "kalendarsko",
    "ukrainianTranslation": "календарний",
    "exampleSentence": "Kalendarska godina završava u prosincu.",
    "ukrainianTranslationSentence": "Календарний рік закінчується у грудні."
  },
  {
    "maskuline": "kanalizacijski",
    "feminine": "kanalizacijska",
    "neutrum": "kanalizacijsko",
    "ukrainianTranslation": "каналізаційний",
    "exampleSentence": "Radnici su popravljali kanalizacijski sustav u gradu.",
    "ukrainianTranslationSentence": "Працівники ремонтували каналізаційну систему в місті."
  },
  {
    "maskuline": "kaotičan",
    "feminine": "kaotična",
    "neutrum": "kaotično",
    "ukrainianTranslation": "хаотичний",
    "exampleSentence": "Situacija u prometu bila je kaotična zbog snježne oluje.",
    "ukrainianTranslationSentence": "Ситуація на дорогах була хаотичною через снігову бурю."
  },
  {
    "maskuline": "kapitalistički",
    "feminine": "kapitalistička",
    "neutrum": "kapitalističko",
    "ukrainianTranslation": "капіталістичний",
    "exampleSentence": "Kapitalistički sustav dominira u mnogim razvijenim zemljama.",
    "ukrainianTranslationSentence": "Капіталістична система домінує в багатьох розвинених країнах."
  },
  {
    "maskuline": "karakteran",
    "feminine": "karakterna",
    "neutrum": "karakterno",
    "ukrainianTranslation": "характерний",
    "exampleSentence": "On je karakteran čovjek s jasnim moralnim načelima.",
    "ukrainianTranslationSentence": "Він характерна людина з чіткими моральними принципами."
  },
  {
    "maskuline": "kartonski",
    "feminine": "kartonska",
    "neutrum": "kartonsko",
    "ukrainianTranslation": "картонний",
    "exampleSentence": "Pakiranje je stiglo u kartonskoj kutiji.",
    "ukrainianTranslationSentence": "Упаковка прибула в картонній коробці."
  },
  {
    "maskuline": "kazneni",
    "feminine": "kaznena",
    "neutrum": "kazneno",
    "ukrainianTranslation": "кримінальний",
    "exampleSentence": "Sud je izrekao kaznenu presudu za počinitelja.",
    "ukrainianTranslationSentence": "Суд виніс кримінальний вирок виконавцю."
  },
	{
    "maskuline": "keramički",
    "feminine": "keramička",
    "neutrum": "keramičko",
    "ukrainianTranslation": "керамічний",
    "exampleSentence": "Kupili smo keramičke pločice za novu kuhinju.",
    "ukrainianTranslationSentence": "Ми купили керамічну плитку для нової кухні."
  },
  {
    "maskuline": "kirurški",
    "feminine": "kirurška",
    "neutrum": "kirurško",
    "ukrainianTranslation": "хірургічний",
    "exampleSentence": "Kirurški zahvat bio je uspješan.",
    "ukrainianTranslationSentence": "Хірургічна операція пройшла успішно."
  },
  {
    "maskuline": "klizni",
    "feminine": "klizna",
    "neutrum": "klizno",
    "ukrainianTranslation": "ковзний",
    "exampleSentence": "Vrata su klizna kako bi se uštedio prostor.",
    "ukrainianTranslationSentence": "Двері ковзні, щоб зекономити місце."
  },
  {
    "maskuline": "ključan",
    "feminine": "ključna",
    "neutrum": "ključno",
    "ukrainianTranslation": "ключовий",
    "exampleSentence": "Ključan trenutak utakmice bio je u posljednjoj minuti.",
    "ukrainianTranslationSentence": "Ключовий момент матчу стався на останній хвилині."
  },
  {
    "maskuline": "klupski",
    "feminine": "klupska",
    "neutrum": "klupsko",
    "ukrainianTranslation": "клубний",
    "exampleSentence": "Klupski članovi su organizirali zajednički izlet.",
    "ukrainianTranslationSentence": "Члени клубу організували спільну подорож."
  },
  {
    "maskuline": "knjižnični",
    "feminine": "knjižnična",
    "neutrum": "knjižničko",
    "ukrainianTranslation": "бібліотечний",
    "exampleSentence": "Knjižnični fond je proširen s novim naslovima.",
    "ukrainianTranslationSentence": "Бібліотечний фонд було розширено новими назвами."
  },
  {
    "maskuline": "koalicijski",
    "feminine": "koalicijska",
    "neutrum": "koalicijsko",
    "ukrainianTranslation": "коаліційний",
    "exampleSentence": "Koalicijska vlada uspjela je postići dogovor o reformama.",
    "ukrainianTranslationSentence": "Коаліційний уряд зміг досягти згоди щодо реформ."
  },
  {
    "maskuline": "kockast",
    "feminine": "kockasta",
    "neutrum": "kockasto",
    "ukrainianTranslation": "квадратний",
    "exampleSentence": "Njegova nova košulja imala je kockasti uzorak.",
    "ukrainianTranslationSentence": "Його нова сорочка мала квадратний візерунок."
  },
  {
    "maskuline": "kolonijalan",
    "feminine": "kolonijalna",
    "neutrum": "kolonijalno",
    "ukrainianTranslation": "колоніальний",
    "exampleSentence": "Kolonijalna arhitektura bila je vrlo utjecajna u prošlim stoljećima.",
    "ukrainianTranslationSentence": "Колоніальна архітектура була дуже впливовою в минулих століттях."
  },
  {
    "maskuline": "kombiniran",
    "feminine": "kombinirana",
    "neutrum": "kombinirano",
    "ukrainianTranslation": "комбінований",
    "exampleSentence": "Imali su kombinirani pristup problemu, koristeći više metoda.",
    "ukrainianTranslationSentence": "Вони використовували комбінований підхід до проблеми, використовуючи кілька методів."
  },
	{
    "maskuline": "komercijalan",
    "feminine": "komercijalna",
    "neutrum": "komercijalno",
    "ukrainianTranslation": "комерційний",
    "exampleSentence": "Komercijalni uspjeh filma nadmašio je sva očekivanja.",
    "ukrainianTranslationSentence": "Комерційний успіх фільму перевершив усі очікування."
  },
  {
    "maskuline": "komorni",
    "feminine": "komorna",
    "neutrum": "komorno",
    "ukrainianTranslation": "камерний",
    "exampleSentence": "Komorni koncert održan je u intimnom ambijentu.",
    "ukrainianTranslationSentence": "Камерний концерт пройшов в затишній атмосфері."
  },
  {
    "maskuline": "kompjuterski",
    "feminine": "kompjuterska",
    "neutrum": "kompjutersko",
    "ukrainianTranslation": "комп'ютерний",
    "exampleSentence": "Kompjuterski program omogućuje brzu obradu podataka.",
    "ukrainianTranslationSentence": "Комп'ютерна програма дозволяє швидко обробляти дані."
  },
  {
    "maskuline": "konačan",
    "feminine": "konačna",
    "neutrum": "konačno",
    "ukrainianTranslation": "остаточний",
    "exampleSentence": "Konačna odluka donesena je nakon dugih pregovora.",
    "ukrainianTranslationSentence": "Остаточне рішення було прийнято після довгих переговорів."
  },
  {
    "maskuline": "konceptualan",
    "feminine": "konceptualna",
    "neutrum": "konceptualno",
    "ukrainianTranslation": "концептуальний",
    "exampleSentence": "Njegov konceptualan pristup umjetnosti bio je inovativan.",
    "ukrainianTranslationSentence": "Його концептуальний підхід до мистецтва був інноваційним."
  },
  {
    "maskuline": "koncertni",
    "feminine": "koncertna",
    "neutrum": "koncertno",
    "ukrainianTranslation": "концертний",
    "exampleSentence": "Koncertna dvorana bila je ispunjena do posljednjeg mjesta.",
    "ukrainianTranslationSentence": "Концертна зала була заповнена до останнього місця."
  },
  {
    "maskuline": "konferencijski",
    "feminine": "konferencijska",
    "neutrum": "konferencijsko",
    "ukrainianTranslation": "конференційний",
    "exampleSentence": "Konferencijska sala bila je opremljena najmodernijom tehnologijom.",
    "ukrainianTranslationSentence": "Конференційний зал був обладнаний найсучаснішою технікою."
  },
  {
    "maskuline": "konkretan",
    "feminine": "konkretna",
    "neutrum": "konkretno",
    "ukrainianTranslation": "конкретний",
    "exampleSentence": "Pitanje je zahtijevalo konkretan odgovor bez okolišanja.",
    "ukrainianTranslationSentence": "Питання вимагало конкретної відповіді без ухилянь."
  },
  {
    "maskuline": "konstantan",
    "feminine": "konstantna",
    "neutrum": "konstantno",
    "ukrainianTranslation": "постійний",
    "exampleSentence": "Konstantan rad na projektu donio je uspješne rezultate.",
    "ukrainianTranslationSentence": "Постійна робота над проєктом принесла успішні результати."
  },
  {
    "maskuline": "konstruktivan",
    "feminine": "konstruktivna",
    "neutrum": "konstruktivno",
    "ukrainianTranslation": "конструктивний",
    "exampleSentence": "Imali smo konstruktivan razgovor o budućim planovima.",
    "ukrainianTranslationSentence": "Ми мали конструктивну розмову про майбутні плани."
  },
	{
    "maskuline": "kontaktan",
    "feminine": "kontaktna",
    "neutrum": "kontaktno",
    "ukrainianTranslation": "контактний",
    "exampleSentence": "Kontaktan sport kao što je ragbi zahtijeva puno fizičke snage.",
    "ukrainianTranslationSentence": "Контактний спорт, як регбі, вимагає багато фізичної сили."
  },
  {
    "maskuline": "kontinentalan",
    "feminine": "kontinentalna",
    "neutrum": "kontinentalno",
    "ukrainianTranslation": "континентальний",
    "exampleSentence": "Kontinentalna klima karakteristična je za ovaj dio zemlje.",
    "ukrainianTranslationSentence": "Континентальний клімат характерний для цієї частини країни."
  },
  {
    "maskuline": "kontracepcijski",
    "feminine": "kontracepcijska",
    "neutrum": "kontracepcijsko",
    "ukrainianTranslation": "контрацептивний",
    "exampleSentence": "Kontracepcijska sredstva pomažu u planiranju obitelji.",
    "ukrainianTranslationSentence": "Контрацептивні засоби допомагають у плануванні сім'ї."
  },
  {
    "maskuline": "kontroverzan",
    "feminine": "kontroverzna",
    "neutrum": "kontroverzno",
    "ukrainianTranslation": "суперечливий",
    "exampleSentence": "Njegov govor izazvao je kontroverzne reakcije u javnosti.",
    "ukrainianTranslationSentence": "Його промова викликала суперечливі реакції в суспільстві."
  },
  {
    "maskuline": "kopnen",
    "feminine": "kopnena",
    "neutrum": "kopneno",
    "ukrainianTranslation": "сухопутний",
    "exampleSentence": "Kopnena vojska imala je ključnu ulogu u operaciji.",
    "ukrainianTranslationSentence": "Сухопутні війська відіграли ключову роль в операції."
  },
  {
    "maskuline": "koristan",
    "feminine": "korisna",
    "neutrum": "korisno",
    "ukrainianTranslation": "корисний",
    "exampleSentence": "Ovaj alat je vrlo koristan za svakodnevne zadatke.",
    "ukrainianTranslationSentence": "Цей інструмент дуже корисний для щоденних завдань."
  },
  {
    "maskuline": "korumpiran",
    "feminine": "korumpirana",
    "neutrum": "korumpirano",
    "ukrainianTranslation": "корумпований",
    "exampleSentence": "Korumpirani političari su izgubili podršku naroda.",
    "ukrainianTranslationSentence": "Корумповані політики втратили підтримку народу."
  },
  {
    "maskuline": "korupcijski",
    "feminine": "korupcijska",
    "neutrum": "korupcijsko",
    "ukrainianTranslation": "корупційний",
    "exampleSentence": "Vlada provodi istrage zbog korupcijskih skandala.",
    "ukrainianTranslationSentence": "Уряд проводить розслідування через корупційні скандали."
  },
  {
    "maskuline": "kozmetički",
    "feminine": "kozmetička",
    "neutrum": "kozmetičko",
    "ukrainianTranslation": "косметичний",
    "exampleSentence": "Kozmetički proizvodi moraju proći stroge testove sigurnosti.",
    "ukrainianTranslationSentence": "Косметичні продукти повинні пройти суворі тести на безпеку."
  },
  {
    "maskuline": "kraljevski",
    "feminine": "kraljevska",
    "neutrum": "kraljevsko",
    "ukrainianTranslation": "королівський",
    "exampleSentence": "Kraljevska obitelj prisustvovala je svečanoj ceremoniji.",
    "ukrainianTranslationSentence": "Королівська родина була присутня на урочистій церемонії."
  },
	{
    "maskuline": "kratak",
    "feminine": "kratka",
    "neutrum": "kratko",
    "ukrainianTranslation": "короткий",
    "exampleSentence": "Njegov govor bio je kratak, ali jasan.",
    "ukrainianTranslationSentence": "Його промова була короткою, але чіткою."
  },
  {
    "maskuline": "kratkoročan",
    "feminine": "kratkoročna",
    "neutrum": "kratkoročno",
    "ukrainianTranslation": "короткостроковий",
    "exampleSentence": "Ova investicija donosi kratkoročne rezultate.",
    "ukrainianTranslationSentence": "Ця інвестиція приносить короткострокові результати."
  },
  {
    "maskuline": "kratkotrajan",
    "feminine": "kratkotrajna",
    "neutrum": "kratkotrajno",
    "ukrainianTranslation": "короткочасний",
    "exampleSentence": "Kratkotrajna oluja oštetila je nekoliko kuća.",
    "ukrainianTranslationSentence": "Короткочасна буря пошкодила кілька будинків."
  },
  {
    "maskuline": "krilni",
    "feminine": "krilna",
    "neutrum": "krilno",
    "ukrainianTranslation": "крилатий",
    "exampleSentence": "Krilni napadač je postigao gol u posljednjim minutama utakmice.",
    "ukrainianTranslationSentence": "Крилатий нападник забив гол у останні хвилини матчу."
  },
  {
    "maskuline": "kriminalan",
    "feminine": "kriminalna",
    "neutrum": "kriminalno",
    "ukrainianTranslation": "кримінальний",
    "exampleSentence": "Kriminalna organizacija je raskrinkana nakon dugotrajne istrage.",
    "ukrainianTranslationSentence": "Кримінальна організація була розкрита після тривалого розслідування."
  },
  {
    "maskuline": "kristalan",
    "feminine": "kristalna",
    "neutrum": "kristalno",
    "ukrainianTranslation": "кришталевий",
    "exampleSentence": "Voda u jezeru bila je kristalno čista.",
    "ukrainianTranslationSentence": "Вода в озері була кришталево чистою."
  },
  {
    "maskuline": "kriv",
    "feminine": "kriva",
    "neutrum": "krivo",
    "ukrainianTranslation": "винний",
    "exampleSentence": "Sud je odlučio da je optuženi kriv za počinjeno djelo.",
    "ukrainianTranslationSentence": "Суд вирішив, що обвинувачений винний у скоєному злочині."
  },
  {
    "maskuline": "križarski",
    "feminine": "križarska",
    "neutrum": "križarsko",
    "ukrainianTranslation": "хрестовий",
    "exampleSentence": "Proučavali su križarske ratove tijekom povijesne lekcije.",
    "ukrainianTranslationSentence": "Вони вивчали хрестові походи під час уроку історії."
  },
  {
    "maskuline": "krovni",
    "feminine": "krovna",
    "neutrum": "krovno",
    "ukrainianTranslation": "даховий",
    "exampleSentence": "Krovni prozori omogućuju dodatno osvjetljenje u potkrovlju.",
    "ukrainianTranslationSentence": "Дахові вікна забезпечують додаткове освітлення в мансарді."
  },
  {
    "maskuline": "krucijalan",
    "feminine": "krucijalna",
    "neutrum": "krucijalno",
    "ukrainianTranslation": "вирішальний",
    "exampleSentence": "Krucijalan trenutak u utakmici bio je dosuđeni penal.",
    "ukrainianTranslationSentence": "Вирішальний момент у матчі був призначений пенальті."
  }
]
